odoo10_addon_sale_revert_done-10.0.1.0.1-py3.8-nspkg.pth
odoo/addons/sale_revert_done/README.rst
odoo/addons/sale_revert_done/__init__.py
odoo/addons/sale_revert_done/__manifest__.py
odoo/addons/sale_revert_done/i18n/ca.po
odoo/addons/sale_revert_done/i18n/de.po
odoo/addons/sale_revert_done/i18n/el_GR.po
odoo/addons/sale_revert_done/i18n/es.po
odoo/addons/sale_revert_done/i18n/es_ES.po
odoo/addons/sale_revert_done/i18n/es_VE.po
odoo/addons/sale_revert_done/i18n/fi.po
odoo/addons/sale_revert_done/i18n/fr.po
odoo/addons/sale_revert_done/i18n/hr.po
odoo/addons/sale_revert_done/i18n/hr_HR.po
odoo/addons/sale_revert_done/i18n/hu.po
odoo/addons/sale_revert_done/i18n/it.po
odoo/addons/sale_revert_done/i18n/nl.po
odoo/addons/sale_revert_done/i18n/nl_NL.po
odoo/addons/sale_revert_done/i18n/pt.po
odoo/addons/sale_revert_done/i18n/pt_BR.po
odoo/addons/sale_revert_done/i18n/ro.po
odoo/addons/sale_revert_done/i18n/sale_revert_done.pot
odoo/addons/sale_revert_done/i18n/sk.po
odoo/addons/sale_revert_done/i18n/sl.po
odoo/addons/sale_revert_done/i18n/tr.po
odoo/addons/sale_revert_done/i18n/tr_TR.po
odoo/addons/sale_revert_done/i18n/vi_VN.po
odoo/addons/sale_revert_done/i18n/zh_CN.po
odoo/addons/sale_revert_done/models/__init__.py
odoo/addons/sale_revert_done/models/sale_order.py
odoo/addons/sale_revert_done/static/description/icon.png
odoo/addons/sale_revert_done/tests/__init__.py
odoo/addons/sale_revert_done/tests/test_sale_revert_done.py
odoo/addons/sale_revert_done/views/sale_revert_done_view.xml
odoo10_addon_sale_revert_done-10.0.1.0.1.dist-info/METADATA
odoo10_addon_sale_revert_done-10.0.1.0.1.dist-info/WHEEL
odoo10_addon_sale_revert_done-10.0.1.0.1.dist-info/namespace_packages.txt
odoo10_addon_sale_revert_done-10.0.1.0.1.dist-info/top_level.txt
odoo10_addon_sale_revert_done-10.0.1.0.1.dist-info/RECORD
